AuthBarn/AuthBarn.py
AuthBarn/__init__.py
AuthBarn/config.py
AuthBarn/logger.py
AuthBarn/test.py
AuthBarn/data/permission.json
AuthBarn/logfiles/general_logs.log
AuthBarn/logfiles/user_logs.log
authbarn-0.2.8.dist-info/METADATA
authbarn-0.2.8.dist-info/WHEEL
authbarn-0.2.8.dist-info/top_level.txt
authbarn-0.2.8.dist-info/RECORD
