Metadata-Version: 2.4
Name: AuthBarn
Version: 0.2.8
Summary: User authentication and role-based management.
Home-page: https://github.com/Barndalion/AuthBarn
Author: Darell Barnes
Author-email: Darell Barnes <darellbarnes450@gmail.com>
License: MIT
Requires-Python: >=3.6
Requires-Dist: bcrypt
Requires-Dist: PyJWT
Requires-Dist: mysql-connector-python
Requires-Dist: python-dotenv
Dynamic: author
Dynamic: home-page
Dynamic: requires-python
